tmcnt/__init__.py
tmcnt/utils.py
tmcnt-0.1.dist-info/licenses/LICENSE
tmcnt-0.1.dist-info/METADATA
tmcnt-0.1.dist-info/WHEEL
tmcnt-0.1.dist-info/top_level.txt
tmcnt-0.1.dist-info/RECORD
