Metadata-Version: 2.4
Name: tmcnt
Version: 0.1
Summary: program execution time count
Author: Arsen
License: MIT
Requires-Python: >=3.8
License-File: LICENSE
Dynamic: author
Dynamic: description
Dynamic: description-content-type
Dynamic: license
Dynamic: license-file
Dynamic: requires-python
Dynamic: summary
